{"stat.chestOpened":3,"stat.useItem.minecraft.lapis_block":5908,"stat.walkOneCm":250834,"stat.useItem.minecraft.chest":1,"achievement.openInventory":1,"stat.leaveGame":7,"stat.flyOneCm":334071,"stat.jump":974,"stat.swimOneCm":392,"stat.playOneMinute":40026,"stat.climbOneCm":1400,"stat.crouchOneCm":11969,"stat.useItem.minecraft.wool":8,"stat.timeSinceDeath":40026,"stat.useItem.minecraft.dirt":9,"stat.sprintOneCm":209438,"achievement.exploreAllBiomes":{"value":0,"progress":["Beach","River","Ocean","Desert","Savanna","Deep Ocean"]},"stat.diveOneCm":5019}