{"stat.chestOpened":1,"stat.useItem.minecraft.lapis_block":42,"stat.walkOneCm":21263,"achievement.openInventory":5,"stat.leaveGame":7,"stat.damageTaken":781,"stat.mobKills":1,"stat.entityKilledBy.Creeper":1,"stat.flyOneCm":55407,"stat.deaths":2,"stat.jump":220,"stat.swimOneCm":798,"stat.playOneMinute":5830,"stat.fallOneCm":4901,"stat.damageDealt":345,"stat.crouchOneCm":203,"stat.useItem.minecraft.wool":180,"stat.timeSinceDeath":3958,"stat.sprintOneCm":8844,"achievement.exploreAllBiomes":{"value":0,"progress":["Beach","DesertHills","Desert"]}}